setup.py
mutiplexing/__init__.py
mutiplexing/mutiplexing.py
mutiplexing.egg-info/PKG-INFO
mutiplexing.egg-info/SOURCES.txt
mutiplexing.egg-info/dependency_links.txt
mutiplexing.egg-info/requires.txt
mutiplexing.egg-info/top_level.txt